odoo/addons/partner_default_delivery_carrier/README.rst
odoo/addons/partner_default_delivery_carrier/__init__.py
odoo/addons/partner_default_delivery_carrier/__manifest__.py
odoo/addons/partner_default_delivery_carrier/i18n/es.po
odoo/addons/partner_default_delivery_carrier/i18n/it.po
odoo/addons/partner_default_delivery_carrier/i18n/partner_default_delivery_carrier.pot
odoo/addons/partner_default_delivery_carrier/models/__init__.py
odoo/addons/partner_default_delivery_carrier/models/res_config_settings.py
odoo/addons/partner_default_delivery_carrier/readme/CONFIGURE.rst
odoo/addons/partner_default_delivery_carrier/readme/CONTRIBUTORS.rst
odoo/addons/partner_default_delivery_carrier/readme/DESCRIPTION.rst
odoo/addons/partner_default_delivery_carrier/static/description/icon.png
odoo/addons/partner_default_delivery_carrier/static/description/index.html
odoo/addons/partner_default_delivery_carrier/tests/__init__.py
odoo/addons/partner_default_delivery_carrier/tests/test_default_delivery_carrier.py
odoo/addons/partner_default_delivery_carrier/views/res_config_settings.xml
odoo14_addon_partner_default_delivery_carrier-14.0.1.0.1.dev10.dist-info/METADATA
odoo14_addon_partner_default_delivery_carrier-14.0.1.0.1.dev10.dist-info/WHEEL
odoo14_addon_partner_default_delivery_carrier-14.0.1.0.1.dev10.dist-info/top_level.txt
odoo14_addon_partner_default_delivery_carrier-14.0.1.0.1.dev10.dist-info/RECORD
